{"pools":[{"rolls":1,"entries":[{"type":"alternatives","children":[{"type":"loot_table","value":"bs.block:internal/group_50","functions":[{"function":"set_custom_data","tag":"{\"_\":{1:\"conditional=false,\"},properties:{conditional:\"false\"}}"}],"conditions":[{"condition":"location_check","predicate":{"block":{"state":{"conditional":"false"}}}}]},{"type":"loot_table","value":"bs.block:internal/group_50","functions":[{"function":"set_custom_data","tag":"{\"_\":{1:\"conditional=true,\"},properties:{conditional:\"true\"}}"}]}]}]}]}