{"pools":[{"rolls":1,"entries":[{"type":"alternatives","children":[{"type":"loot_table","value":"bs.block:internal/group_114","functions":[{"function":"set_custom_data","tag":"{\"_\":{2:\"shape=north_south,\"},properties:{shape:\"north_south\"}}"}],"conditions":[{"condition":"location_check","predicate":{"block":{"state":{"shape":"north_south"}}}}]},{"type":"loot_table","value":"bs.block:internal/group_114","functions":[{"function":"set_custom_data","tag":"{\"_\":{2:\"shape=east_west,\"},properties:{shape:\"east_west\"}}"}],"conditions":[{"condition":"location_check","predicate":{"block":{"state":{"shape":"east_west"}}}}]},{"type":"loot_table","value":"bs.block:internal/group_114","functions":[{"function":"set_custom_data","tag":"{\"_\":{2:\"shape=ascending_east,\"},properties:{shape:\"ascending_east\"}}"}],"conditions":[{"condition":"location_check","predicate":{"block":{"state":{"shape":"ascending_east"}}}}]},{"type":"loot_table","value":"bs.block:internal/group_114","functions":[{"function":"set_custom_data","tag":"{\"_\":{2:\"shape=ascending_west,\"},properties:{shape:\"ascending_west\"}}"}],"conditions":[{"condition":"location_check","predicate":{"block":{"state":{"shape":"ascending_west"}}}}]},{"type":"loot_table","value":"bs.block:internal/group_114","functions":[{"function":"set_custom_data","tag":"{\"_\":{2:\"shape=ascending_north,\"},properties:{shape:\"ascending_north\"}}"}],"conditions":[{"condition":"location_check","predicate":{"block":{"state":{"shape":"ascending_north"}}}}]},{"type":"loot_table","value":"bs.block:internal/group_114","functions":[{"function":"set_custom_data","tag":"{\"_\":{2:\"shape=ascending_south,\"},properties:{shape:\"ascending_south\"}}"}]}]}]}]}